<?xml version="1.0" encoding="UTF-8"?>
<b:beans 
	xmlns="urn:schemas:morphis:foundations:formmodel"
	xmlns:xsi="http://www.w3.org/2001/XMLSchema-instance" 
	xmlns:b="http://www.springframework.org/schema/beans"
	xsi:schemaLocation="http://www.springframework.org/schema/beans http://www.springframework.org/schema/beans/spring-beans.xsd urn:schemas:morphis:foundations:formmodel http://www.morphis-tech.com/schema/foundations/formmodel.xsd">
	
		<b:import resource="classpath:/net/hedtech/banner/finance/common/Foqaddr/model/FORM_HEADER.Manager.Config.xml"/>
		<b:import resource="classpath:/net/hedtech/banner/finance/common/Foqaddr/model/KEY_BLOCK.Manager.Config.xml"/>
		<b:import resource="classpath:/net/hedtech/banner/finance/common/Foqaddr/model/SPRADDR.Manager.Config.xml"/>
		<b:import resource="classpath:/net/hedtech/banner/finance/common/Foqaddr/model/BUTTON_CONTROL_BLOCK.Manager.Config.xml"/>
	
	<formModel id="FOQADDR.Model.Config" name="FOQADDR">
		<modelClass>net.hedtech.banner.finance.common.Foqaddr.model.FoqaddrModel</modelClass>
		<parameters>
		</parameters>
		
		<businessObjects>
			<businessObject name="FORM_HEADER" manager="FORM_HEADER.Manager.Config">
		
		
			</businessObject>
			<businessObject name="KEY_BLOCK" manager="KEY_BLOCK.Manager.Config">
		
		
			</businessObject>
			<businessObject name="SPRADDR" manager="SPRADDR.Manager.Config">
		
		
			</businessObject>
			<businessObject name="BUTTON_CONTROL_BLOCK" manager="BUTTON_CONTROL_BLOCK.Manager.Config">
		
		
			</businessObject>
		</businessObjects>
	</formModel>
</b:beans>
